swarup_calculator/__init__.py
swarup_calculator-0.1.dist-info/LICENSE.txt
swarup_calculator-0.1.dist-info/METADATA
swarup_calculator-0.1.dist-info/WHEEL
swarup_calculator-0.1.dist-info/top_level.txt
swarup_calculator-0.1.dist-info/RECORD
