Metadata-Version: 2.1
Name: swarup-calculator
Version: 0.1
Summary: A sample Python package to calculate
Home-page: UNKNOWN
Author: Swarup Adhikary
Author-email: bdnsbank@gmail.com
License: UNKNOWN
Platform: UNKNOWN
